nerdstorage/__init__.py
nerdstorage/__main__.py
nerdstorage/auth.py
nerdstorage/config.py
nerdstorage/handlers.py
nerdstorage/models.py
nerdstorage/views.py
nerdstorage/hash/hash.py
nerdstorage/static/flow.min.js
nerdstorage/static/icon.png
nerdstorage/static/large_file.js
nerdstorage/static/script.js
nerdstorage/static/style.css
nerdstorage/templates/base.html
nerdstorage/templates/index.html
nerdstorage/templates/large_file.html
nerdstorage/templates/login.html
nerdstorage/tmp/tmp
nerdstorage/utils/__init__.py
nerdstorage/utils/config_util.py
nerdstorage/utils/security_util.py
nerdstorage/utils/util.py
Nerd_Storage-0.2.1.dist-info/LICENSE
Nerd_Storage-0.2.1.dist-info/METADATA
Nerd_Storage-0.2.1.dist-info/WHEEL
Nerd_Storage-0.2.1.dist-info/entry_points.txt
Nerd_Storage-0.2.1.dist-info/top_level.txt
Nerd_Storage-0.2.1.dist-info/RECORD
