Metadata-Version: 2.1
Name: Nerd-Storage
Version: 0.2.1
Summary: A simple LAN storage.
Home-page: https://github.com/0xHaru/Nerd-Storage
Author: 0xHaru
Author-email: 0xharu.git@gmail.com
License: GPLv3
Project-URL: Bug Tracker, https://github.com/0xHaru/Nerd-Storage/issues
Keywords: storage flask webserver homeserver
Platform: UNKNOWN
Classifier: Programming Language :: Python :: 3
Classifier: Programming Language :: Python :: 3.6
Classifier: Programming Language :: Python :: 3.7
Classifier: Programming Language :: Python :: 3.8
Classifier: Programming Language :: Python :: 3.9
Classifier: Programming Language :: Python :: 3.10
Classifier: Operating System :: POSIX :: Linux
Classifier: License :: OSI Approved :: GNU General Public License v3 (GPLv3)
Requires-Python: >=3.6
License-File: LICENSE
Requires-Dist: flask
Requires-Dist: flask-login
Requires-Dist: jinja2
